pyfop/__init__.py
pyfop/argparser.py
pyfop/aspect.py
pyfop/cache.py
pyfop/core.py
pyfop/execution.py
pyfop/utils.py
tests/__init__.py
tests/test.py
pyfop-0.3.5.dist-info/LICENSE.txt
pyfop-0.3.5.dist-info/METADATA
pyfop-0.3.5.dist-info/WHEEL
pyfop-0.3.5.dist-info/top_level.txt
pyfop-0.3.5.dist-info/RECORD
