Metadata-Version: 2.1
Name: pyfop
Version: 0.3.5
Summary: A forward-oriented programming paradigm for Python.
Home-page: https://github.com/maniospas/pyfop
Author: Emmanouil Krasanakis
Author-email: maniospas@hotmail.com
License: Apache 2.0
Keywords: metaprogramming,component-based programming,software as a service
Platform: UNKNOWN
Classifier: Development Status :: 3 - Alpha
Classifier: Programming Language :: Python :: 3
Classifier: License :: OSI Approved :: Apache Software License
Classifier: Operating System :: OS Independent
License-File: LICENSE.txt
Requires-Dist: makefun
